setup.py
shopfloor_toolkit_v3.egg-info/PKG-INFO
shopfloor_toolkit_v3.egg-info/SOURCES.txt
shopfloor_toolkit_v3.egg-info/dependency_links.txt
shopfloor_toolkit_v3.egg-info/not-zip-safe
shopfloor_toolkit_v3.egg-info/requires.txt
shopfloor_toolkit_v3.egg-info/top_level.txt
toolkit/__init__.py
toolkit/api.py
toolkit/code_status_tkt.py
toolkit/connection_setting.py
toolkit/utility.py