Metadata-Version: 2.1
Name: shopfloor-toolkit-v3
Version: 0.1
Summary: Toolkit for the Shopfloor endpoints.
Author: Medulla
